mychat-0.2.6.dist-info/DESCRIPTION.rst
mychat-0.2.6.dist-info/METADATA
mychat-0.2.6.dist-info/RECORD
mychat-0.2.6.dist-info/WHEEL
mychat-0.2.6.dist-info/entry_points.txt
mychat-0.2.6.dist-info/metadata.json
mychat-0.2.6.dist-info/top_level.txt
mychat_client/1.py
mychat_client/__init__.py
mychat_client/client.py
mychat_client/client_console.py
mychat_client/client_gui (2).py
mychat_client/client_gui.py
mychat_client/handlers.py
mychat_client/sv_main.ui
mychat_jim/__init__.py
mychat_jim/config.py
mychat_jim/core.py
mychat_jim/exceptions.py
mychat_jim/utils.py
mychat_log/__init__.py
mychat_log/client_log_config.py
mychat_log/decorators.py
mychat_log/server_log_config.py
mychat_log/test_decorators.py
mychat_repo/__init__.py
mychat_repo/server_errors.py
mychat_repo/server_models.py
mychat_repo/server_repo.py
mychat_server/__init__.py
mychat_server/server.py
