Metadata-Version: 2.0
Name: mychat
Version: 0.2.6
Summary: Simple messenger.
Home-page: UNKNOWN
Author: UNKNOWN
Author-email: UNKNOWN
License: MIT
Platform: UNKNOWN
Requires-Dist: PyQt5 (>=5.9)
Requires-Dist: SQLAlchemy (>=1.1.15)
